{"openapi":"3.0.2","info":{"title":"FastAPI","version":"0.1.0"},"paths":{"/rootservers/{root_server_id}/meetings/changes":{"get":{"summary":"List Meeting Changes","operationId":"list_meeting_changes_rootservers__root_server_id__meetings_changes_get","parameters":[{"required":true,"schema":{"title":"Root Server Id","type":"integer"},"name":"root_server_id","in":"path"},{"required":true,"schema":{"title":"Start Date","type":"string","format":"date"},"name":"start_date","in":"query"},{"required":false,"schema":{"title":"End Date","type":"string","format":"date"},"name":"end_date","in":"query"},{"required":false,"schema":{"title":"Service Body Bmlt Ids","type":"array","items":{"type":"integer"}},"name":"service_body_bmlt_ids","in":"query"},{"required":false,"schema":{"title":"Exclude World Id Updates","type":"boolean","default":false},"name":"exclude_world_id_updates","in":"query"}],"responses":{"200":{"description":"Successful Response","content":{"application/json":{"schema":{"$ref":"#/components/schemas/MeetingChangesResponse"}}}},"422":{"description":"Validation Error","content":{"application/json":{"schema":{"$ref":"#/components/schemas/HTTPValidationError"}}}}},"security":[{"OAuth2PasswordBearer":[]}]}},"/rootservers/{root_server_id}/snapshots/{date}/formats":{"get":{"summary":"List Snapshot Formats","operationId":"list_snapshot_formats_rootservers__root_server_id__snapshots__date__formats_get","parameters":[{"required":true,"schema":{"title":"Root Server Id","type":"integer"},"name":"root_server_id","in":"path"},{"required":true,"schema":{"title":"Date","type":"string","format":"date"},"name":"date","in":"path"}],"responses":{"200":{"description":"Successful Response","content":{"application/json":{"schema":{"title":"Response List Snapshot Formats Rootservers  Root Server Id  Snapshots  Date  Formats Get","type":"array","items":{"$ref":"#/components/schemas/Format"}}}}},"422":{"description":"Validation Error","content":{"application/json":{"schema":{"$ref":"#/components/schemas/HTTPValidationError"}}}}},"security":[{"OAuth2PasswordBearer":[]}]}},"/token":{"post":{"summary":"Create Auth Token","operationId":"create_auth_token_token_post","requestBody":{"content":{"application/x-www-form-urlencoded":{"schema":{"$ref":"#/components/schemas/Body_create_auth_token_token_post"}}},"required":true},"responses":{"200":{"description":"Successful Response","content":{"application/json":{"schema":{"$ref":"#/components/schemas/Token"}}}},"422":{"description":"Validation Error","content":{"application/json":{"schema":{"$ref":"#/components/schemas/HTTPValidationError"}}}}}}},"/logout":{"post":{"summary":"Logout","operationId":"logout_logout_post","requestBody":{"content":{"application/json":{"schema":{"$ref":"#/components/schemas/Logout"}}},"required":true},"responses":{"200":{"description":"Successful Response"},"422":{"description":"Validation Error","content":{"application/json":{"schema":{"$ref":"#/components/schemas/HTTPValidationError"}}}}},"security":[{"OAuth2PasswordBearer":[]}]}},"/rootservers/{root_server_id}/snapshots/{date}/meetings":{"get":{"summary":"List Snapshot Meetings","operationId":"list_snapshot_meetings_rootservers__root_server_id__snapshots__date__meetings_get","parameters":[{"required":true,"schema":{"title":"Root Server Id","type":"integer"},"name":"root_server_id","in":"path"},{"required":true,"schema":{"title":"Date","type":"string","format":"date"},"name":"date","in":"path"},{"required":false,"schema":{"title":"Service Body Bmlt Ids","type":"array","items":{"type":"integer"}},"name":"service_body_bmlt_ids","in":"query"}],"responses":{"200":{"description":"Successful Response","content":{"application/json":{"schema":{"title":"Response List Snapshot Meetings Rootservers  Root Server Id  Snapshots  Date  Meetings Get","type":"array","items":{"$ref":"#/components/schemas/Meeting"}}}}},"422":{"description":"Validation Error","content":{"application/json":{"schema":{"$ref":"#/components/schemas/HTTPValidationError"}}}}},"security":[{"OAuth2PasswordBearer":[]}]}},"/meetings/nawscodes":{"get":{"summary":"List Meeting Naws Codes","operationId":"list_meeting_naws_codes_meetings_nawscodes_get","responses":{"200":{"description":"Successful Response","content":{"application/json":{"schema":{"title":"Response List Meeting Naws Codes Meetings Nawscodes Get","type":"array","items":{"$ref":"#/components/schemas/NawsCode"}}}}}},"security":[{"OAuth2PasswordBearer":[]}]}},"/formats/nawscodes":{"get":{"summary":"List Format Naws Codes","operationId":"list_format_naws_codes_formats_nawscodes_get","responses":{"200":{"description":"Successful Response","content":{"application/json":{"schema":{"title":"Response List Format Naws Codes Formats Nawscodes Get","type":"array","items":{"$ref":"#/components/schemas/NawsCode"}}}}}},"security":[{"OAuth2PasswordBearer":[]}]}},"/servicebodies/nawscodes":{"get":{"summary":"List Service Body Naws Codes","operationId":"list_service_body_naws_codes_servicebodies_nawscodes_get","responses":{"200":{"description":"Successful Response","content":{"application/json":{"schema":{"title":"Response List Service Body Naws Codes Servicebodies Nawscodes Get","type":"array","items":{"$ref":"#/components/schemas/NawsCode"}}}}}},"security":[{"OAuth2PasswordBearer":[]}]}},"/rootservers/{root_server_id}/meetings/nawscodes":{"get":{"summary":"List Server Meeting Naws Codes","operationId":"list_server_meeting_naws_codes_rootservers__root_server_id__meetings_nawscodes_get","parameters":[{"required":true,"schema":{"title":"Root Server Id","type":"integer"},"name":"root_server_id","in":"path"}],"responses":{"200":{"description":"Successful Response","content":{"application/json":{"schema":{"title":"Response List Server Meeting Naws Codes Rootservers  Root Server Id  Meetings Nawscodes Get","type":"array","items":{"$ref":"#/components/schemas/NawsCode"}}}}},"422":{"description":"Validation Error","content":{"application/json":{"schema":{"$ref":"#/components/schemas/HTTPValidationError"}}}}},"security":[{"OAuth2PasswordBearer":[]}]},"post":{"summary":"Create Meeting Naws Code","operationId":"create_meeting_naws_code_rootservers__root_server_id__meetings_nawscodes_post","parameters":[{"required":true,"schema":{"title":"Root Server Id","type":"integer"},"name":"root_server_id","in":"path"}],"requestBody":{"content":{"application/json":{"schema":{"$ref":"#/components/schemas/NawsCodeCreate"}}},"required":true},"responses":{"201":{"description":"Successful Response","content":{"application/json":{"schema":{"$ref":"#/components/schemas/NawsCode"}}}},"422":{"description":"Validation Error","content":{"application/json":{"schema":{"$ref":"#/components/schemas/HTTPValidationError"}}}}},"security":[{"OAuth2PasswordBearer":[]}]},"patch":{"summary":"Batch Update Meeting Naws Codes","operationId":"batch_update_meeting_naws_codes_rootservers__root_server_id__meetings_nawscodes_patch","parameters":[{"required":true,"schema":{"title":"Root Server Id","type":"integer"},"name":"root_server_id","in":"path"}],"requestBody":{"content":{"application/json":{"schema":{"title":"Naws Codes","type":"array","items":{"$ref":"#/components/schemas/NawsCodeCreate"}}}},"required":true},"responses":{"204":{"description":"Successful Response"},"422":{"description":"Validation Error","content":{"application/json":{"schema":{"$ref":"#/components/schemas/HTTPValidationError"}}}}},"security":[{"OAuth2PasswordBearer":[]}]}},"/rootservers/{root_server_id}/formats/nawscodes":{"get":{"summary":"List Server Format Naws Codes","operationId":"list_server_format_naws_codes_rootservers__root_server_id__formats_nawscodes_get","parameters":[{"required":true,"schema":{"title":"Root Server Id","type":"integer"},"name":"root_server_id","in":"path"}],"responses":{"200":{"description":"Successful Response","content":{"application/json":{"schema":{"title":"Response List Server Format Naws Codes Rootservers  Root Server Id  Formats Nawscodes Get","type":"array","items":{"$ref":"#/components/schemas/NawsCode"}}}}},"422":{"description":"Validation Error","content":{"application/json":{"schema":{"$ref":"#/components/schemas/HTTPValidationError"}}}}},"security":[{"OAuth2PasswordBearer":[]}]},"post":{"summary":"Create Format Naws Code","operationId":"create_format_naws_code_rootservers__root_server_id__formats_nawscodes_post","parameters":[{"required":true,"schema":{"title":"Root Server Id","type":"integer"},"name":"root_server_id","in":"path"}],"requestBody":{"content":{"application/json":{"schema":{"$ref":"#/components/schemas/NawsCodeCreate"}}},"required":true},"responses":{"201":{"description":"Successful Response","content":{"application/json":{"schema":{"$ref":"#/components/schemas/NawsCode"}}}},"422":{"description":"Validation Error","content":{"application/json":{"schema":{"$ref":"#/components/schemas/HTTPValidationError"}}}}},"security":[{"OAuth2PasswordBearer":[]}]}},"/rootservers/{root_server_id}/servicebodies/nawscodes":{"get":{"summary":"List Server Service Body Naws Codes","operationId":"list_server_service_body_naws_codes_rootservers__root_server_id__servicebodies_nawscodes_get","parameters":[{"required":true,"schema":{"title":"Root Server Id","type":"integer"},"name":"root_server_id","in":"path"}],"responses":{"200":{"description":"Successful Response","content":{"application/json":{"schema":{"title":"Response List Server Service Body Naws Codes Rootservers  Root Server Id  Servicebodies Nawscodes Get","type":"array","items":{"$ref":"#/components/schemas/NawsCode"}}}}},"422":{"description":"Validation Error","content":{"application/json":{"schema":{"$ref":"#/components/schemas/HTTPValidationError"}}}}},"security":[{"OAuth2PasswordBearer":[]}]},"post":{"summary":"Create Service Body Naws Code","operationId":"create_service_body_naws_code_rootservers__root_server_id__servicebodies_nawscodes_post","parameters":[{"required":true,"schema":{"title":"Root Server Id","type":"integer"},"name":"root_server_id","in":"path"}],"requestBody":{"content":{"application/json":{"schema":{"$ref":"#/components/schemas/NawsCodeCreate"}}},"required":true},"responses":{"201":{"description":"Successful Response","content":{"application/json":{"schema":{"$ref":"#/components/schemas/NawsCode"}}}},"422":{"description":"Validation Error","content":{"application/json":{"schema":{"$ref":"#/components/schemas/HTTPValidationError"}}}}},"security":[{"OAuth2PasswordBearer":[]}]}},"/rootservers/{root_server_id}/meetings/nawscodes/{bmlt_id}":{"get":{"summary":"Get Meeting Naws Code","operationId":"get_meeting_naws_code_rootservers__root_server_id__meetings_nawscodes__bmlt_id__get","parameters":[{"required":true,"schema":{"title":"Root Server Id","type":"integer"},"name":"root_server_id","in":"path"},{"required":true,"schema":{"title":"Bmlt Id","type":"integer"},"name":"bmlt_id","in":"path"}],"responses":{"200":{"description":"Successful Response","content":{"application/json":{"schema":{"$ref":"#/components/schemas/NawsCode"}}}},"422":{"description":"Validation Error","content":{"application/json":{"schema":{"$ref":"#/components/schemas/HTTPValidationError"}}}}},"security":[{"OAuth2PasswordBearer":[]}]},"delete":{"summary":"Delete Meeting Naws Code","operationId":"delete_meeting_naws_code_rootservers__root_server_id__meetings_nawscodes__bmlt_id__delete","parameters":[{"required":true,"schema":{"title":"Root Server Id","type":"integer"},"name":"root_server_id","in":"path"},{"required":true,"schema":{"title":"Bmlt Id","type":"integer"},"name":"bmlt_id","in":"path"}],"responses":{"204":{"description":"Successful Response"},"422":{"description":"Validation Error","content":{"application/json":{"schema":{"$ref":"#/components/schemas/HTTPValidationError"}}}}},"security":[{"OAuth2PasswordBearer":[]}]}},"/rootservers/{root_server_id}/formats/nawscodes/{bmlt_id}":{"get":{"summary":"Get Format Naws Code","operationId":"get_format_naws_code_rootservers__root_server_id__formats_nawscodes__bmlt_id__get","parameters":[{"required":true,"schema":{"title":"Root Server Id","type":"integer"},"name":"root_server_id","in":"path"},{"required":true,"schema":{"title":"Bmlt Id","type":"integer"},"name":"bmlt_id","in":"path"}],"responses":{"200":{"description":"Successful Response","content":{"application/json":{"schema":{"$ref":"#/components/schemas/NawsCode"}}}},"422":{"description":"Validation Error","content":{"application/json":{"schema":{"$ref":"#/components/schemas/HTTPValidationError"}}}}},"security":[{"OAuth2PasswordBearer":[]}]},"delete":{"summary":"Delete Format Naws Code","operationId":"delete_format_naws_code_rootservers__root_server_id__formats_nawscodes__bmlt_id__delete","parameters":[{"required":true,"schema":{"title":"Root Server Id","type":"integer"},"name":"root_server_id","in":"path"},{"required":true,"schema":{"title":"Bmlt Id","type":"integer"},"name":"bmlt_id","in":"path"}],"responses":{"204":{"description":"Successful Response"},"422":{"description":"Validation Error","content":{"application/json":{"schema":{"$ref":"#/components/schemas/HTTPValidationError"}}}}},"security":[{"OAuth2PasswordBearer":[]}]}},"/rootservers/{root_server_id}/servicebodies/nawscodes/{bmlt_id}":{"get":{"summary":"Get Service Body Naws Code","operationId":"get_service_body_naws_code_rootservers__root_server_id__servicebodies_nawscodes__bmlt_id__get","parameters":[{"required":true,"schema":{"title":"Root Server Id","type":"integer"},"name":"root_server_id","in":"path"},{"required":true,"schema":{"title":"Bmlt Id","type":"integer"},"name":"bmlt_id","in":"path"}],"responses":{"200":{"description":"Successful Response","content":{"application/json":{"schema":{"$ref":"#/components/schemas/NawsCode"}}}},"422":{"description":"Validation Error","content":{"application/json":{"schema":{"$ref":"#/components/schemas/HTTPValidationError"}}}}},"security":[{"OAuth2PasswordBearer":[]}]},"delete":{"summary":"Delete Service Body Naws Code","operationId":"delete_service_body_naws_code_rootservers__root_server_id__servicebodies_nawscodes__bmlt_id__delete","parameters":[{"required":true,"schema":{"title":"Root Server Id","type":"integer"},"name":"root_server_id","in":"path"},{"required":true,"schema":{"title":"Bmlt Id","type":"integer"},"name":"bmlt_id","in":"path"}],"responses":{"204":{"description":"Successful Response"},"422":{"description":"Validation Error","content":{"application/json":{"schema":{"$ref":"#/components/schemas/HTTPValidationError"}}}}},"security":[{"OAuth2PasswordBearer":[]}]}},"/rootservers":{"get":{"summary":"List Root Servers","operationId":"list_root_servers_rootservers_get","responses":{"200":{"description":"Successful Response","content":{"application/json":{"schema":{"title":"Response List Root Servers Rootservers Get","type":"array","items":{"$ref":"#/components/schemas/RootServer"}}}}}},"security":[{"OAuth2PasswordBearer":[]}]},"post":{"summary":"Create Root Server","operationId":"create_root_server_rootservers_post","requestBody":{"content":{"application/json":{"schema":{"$ref":"#/components/schemas/RootServerCreate"}}},"required":true},"responses":{"201":{"description":"Successful Response","content":{"application/json":{"schema":{"$ref":"#/components/schemas/RootServer"}}}},"422":{"description":"Validation Error","content":{"application/json":{"schema":{"$ref":"#/components/schemas/HTTPValidationError"}}}}},"security":[{"OAuth2PasswordBearer":[]}]}},"/rootservers/{root_server_id}":{"get":{"summary":"Get Root Server","operationId":"get_root_server_rootservers__root_server_id__get","parameters":[{"required":true,"schema":{"title":"Root Server Id","type":"integer"},"name":"root_server_id","in":"path"}],"responses":{"200":{"description":"Successful Response","content":{"application/json":{"schema":{"$ref":"#/components/schemas/RootServer"}}}},"422":{"description":"Validation Error","content":{"application/json":{"schema":{"$ref":"#/components/schemas/HTTPValidationError"}}}}},"security":[{"OAuth2PasswordBearer":[]}]},"delete":{"summary":"Delete Root Server","operationId":"delete_root_server_rootservers__root_server_id__delete","parameters":[{"required":true,"schema":{"title":"Root Server Id","type":"integer"},"name":"root_server_id","in":"path"}],"responses":{"204":{"description":"Successful Response"},"422":{"description":"Validation Error","content":{"application/json":{"schema":{"$ref":"#/components/schemas/HTTPValidationError"}}}}},"security":[{"OAuth2PasswordBearer":[]}]},"patch":{"summary":"Update Root Server","operationId":"update_root_server_rootservers__root_server_id__patch","parameters":[{"required":true,"schema":{"title":"Root Server Id","type":"integer"},"name":"root_server_id","in":"path"}],"requestBody":{"content":{"application/json":{"schema":{"$ref":"#/components/schemas/RootServerUpdate"}}},"required":true},"responses":{"204":{"description":"Successful Response"},"422":{"description":"Validation Error","content":{"application/json":{"schema":{"$ref":"#/components/schemas/HTTPValidationError"}}}}},"security":[{"OAuth2PasswordBearer":[]}]}},"/rootservers/{root_server_id}/snapshots/{date}/servicebodies":{"get":{"summary":"List Snapshot Service Bodies","operationId":"list_snapshot_service_bodies_rootservers__root_server_id__snapshots__date__servicebodies_get","parameters":[{"required":true,"schema":{"title":"Root Server Id","type":"integer"},"name":"root_server_id","in":"path"},{"required":true,"schema":{"title":"Date","type":"string","format":"date"},"name":"date","in":"path"}],"responses":{"200":{"description":"Successful Response","content":{"application/json":{"schema":{"title":"Response List Snapshot Service Bodies Rootservers  Root Server Id  Snapshots  Date  Servicebodies Get","type":"array","items":{"$ref":"#/components/schemas/ServiceBody"}}}}},"422":{"description":"Validation Error","content":{"application/json":{"schema":{"$ref":"#/components/schemas/HTTPValidationError"}}}}},"security":[{"OAuth2PasswordBearer":[]}]}},"/snapshots":{"get":{"summary":"List Snapshots","operationId":"list_snapshots_snapshots_get","responses":{"200":{"description":"Successful Response","content":{"application/json":{"schema":{"title":"Response List Snapshots Snapshots Get","type":"array","items":{"$ref":"#/components/schemas/Snapshot"}}}}}},"security":[{"OAuth2PasswordBearer":[]}]}},"/rootservers/{root_server_id}/snapshots":{"get":{"summary":"List Server Snapshots","operationId":"list_server_snapshots_rootservers__root_server_id__snapshots_get","parameters":[{"required":true,"schema":{"title":"Root Server Id","type":"integer"},"name":"root_server_id","in":"path"}],"responses":{"200":{"description":"Successful Response","content":{"application/json":{"schema":{"title":"Response List Server Snapshots Rootservers  Root Server Id  Snapshots Get","type":"array","items":{"$ref":"#/components/schemas/Snapshot"}}}}},"422":{"description":"Validation Error","content":{"application/json":{"schema":{"$ref":"#/components/schemas/HTTPValidationError"}}}}},"security":[{"OAuth2PasswordBearer":[]}]}},"/rootservers/{root_server_id}/snapshots/{date}":{"get":{"summary":"Get Server Snapshot","operationId":"get_server_snapshot_rootservers__root_server_id__snapshots__date__get","parameters":[{"required":true,"schema":{"title":"Root Server Id","type":"integer"},"name":"root_server_id","in":"path"},{"required":true,"schema":{"title":"Date","type":"string","format":"date"},"name":"date","in":"path"}],"responses":{"200":{"description":"Successful Response","content":{"application/json":{"schema":{"$ref":"#/components/schemas/Snapshot"}}}},"422":{"description":"Validation Error","content":{"application/json":{"schema":{"$ref":"#/components/schemas/HTTPValidationError"}}}}},"security":[{"OAuth2PasswordBearer":[]}]}},"/users":{"post":{"summary":"Create User","operationId":"create_user_users_post","requestBody":{"content":{"application/json":{"schema":{"$ref":"#/components/schemas/UserCreate"}}},"required":true},"responses":{"201":{"description":"Successful Response","content":{"application/json":{"schema":{"$ref":"#/components/schemas/User"}}}},"422":{"description":"Validation Error","content":{"application/json":{"schema":{"$ref":"#/components/schemas/HTTPValidationError"}}}}},"security":[{"OAuth2PasswordBearer":[]}]}}},"components":{"schemas":{"Body_create_auth_token_token_post":{"title":"Body_create_auth_token_token_post","required":["grant_type"],"type":"object","properties":{"grant_type":{"title":"Grant Type","pattern":"password|refresh_token","type":"string"},"username":{"title":"Username","type":"string"},"password":{"title":"Password","type":"string"},"refresh_token":{"title":"Refresh Token","type":"string"},"scope":{"title":"Scope","type":"string","default":""},"client_id":{"title":"Client Id","type":"string"},"client_secret":{"title":"Client Secret","type":"string"}}},"DayOfWeekEnum":{"title":"DayOfWeekEnum","enum":[1,2,3,4,5,6,7],"type":"integer","description":"An enumeration."},"Format":{"title":"Format","required":["bmlt_id","key_string","name","world_id","naws_code_override"],"type":"object","properties":{"bmlt_id":{"title":"Bmlt Id","type":"integer"},"key_string":{"title":"Key String","type":"string"},"name":{"title":"Name","type":"string"},"world_id":{"title":"World Id","type":"string"},"naws_code_override":{"title":"Naws Code Override","type":"string"}}},"HTTPValidationError":{"title":"HTTPValidationError","type":"object","properties":{"detail":{"title":"Detail","type":"array","items":{"$ref":"#/components/schemas/ValidationError"}}}},"Logout":{"title":"Logout","required":["refresh_token"],"type":"object","properties":{"refresh_token":{"title":"Refresh Token","type":"string"}}},"Meeting":{"title":"Meeting","required":["bmlt_id","name","day","service_body_bmlt_id","venue_type","start_time","duration","time_zone","latitude","longitude","published","world_id","location_text","location_info","location_street","location_city_subsection","location_neighborhood","location_municipality","location_sub_province","location_province","location_postal_code_1","location_nation","train_lines","bus_lines","comments","virtual_meeting_link","phone_meeting_number","virtual_meeting_additional_info","format_bmlt_ids","naws_code_override","service_body","formats","last_changed"],"type":"object","properties":{"bmlt_id":{"title":"Bmlt Id","type":"integer"},"name":{"title":"Name","type":"string"},"day":{"$ref":"#/components/schemas/DayOfWeekEnum"},"service_body_bmlt_id":{"title":"Service Body Bmlt Id","type":"integer"},"venue_type":{"$ref":"#/components/schemas/VenueTypeEnum"},"start_time":{"title":"Start Time","type":"string","format":"time"},"duration":{"title":"Duration","type":"number","format":"time-delta"},"time_zone":{"title":"Time Zone","type":"string"},"latitude":{"title":"Latitude","type":"number"},"longitude":{"title":"Longitude","type":"number"},"published":{"title":"Published","type":"boolean"},"world_id":{"title":"World Id","type":"string"},"location_text":{"title":"Location Text","type":"string"},"location_info":{"title":"Location Info","type":"string"},"location_street":{"title":"Location Street","type":"string"},"location_city_subsection":{"title":"Location City Subsection","type":"string"},"location_neighborhood":{"title":"Location Neighborhood","type":"string"},"location_municipality":{"title":"Location Municipality","type":"string"},"location_sub_province":{"title":"Location Sub Province","type":"string"},"location_province":{"title":"Location Province","type":"string"},"location_postal_code_1":{"title":"Location Postal Code 1","type":"string"},"location_nation":{"title":"Location Nation","type":"string"},"train_lines":{"title":"Train Lines","type":"string"},"bus_lines":{"title":"Bus Lines","type":"string"},"comments":{"title":"Comments","type":"string"},"virtual_meeting_link":{"title":"Virtual Meeting Link","type":"string"},"phone_meeting_number":{"title":"Phone Meeting Number","type":"string"},"virtual_meeting_additional_info":{"title":"Virtual Meeting Additional Info","type":"string"},"format_bmlt_ids":{"title":"Format Bmlt Ids","type":"array","items":{"type":"integer"}},"naws_code_override":{"title":"Naws Code Override","type":"string"},"service_body":{"$ref":"#/components/schemas/ServiceBody"},"formats":{"title":"Formats","type":"array","items":{"$ref":"#/components/schemas/Format"}},"last_changed":{"title":"Last Changed","type":"string","format":"date"}}},"MeetingChangesResponse":{"title":"MeetingChangesResponse","required":["start_date","end_date","events"],"type":"object","properties":{"start_date":{"title":"Start Date","type":"string","format":"date"},"end_date":{"title":"End Date","type":"string","format":"date"},"events":{"title":"Events","type":"array","items":{"$ref":"#/components/schemas/MeetingEvent"}}}},"MeetingEvent":{"title":"MeetingEvent","required":["event_type","old_meeting","new_meeting","changed_fields"],"type":"object","properties":{"event_type":{"$ref":"#/components/schemas/MeetingEventType"},"old_meeting":{"$ref":"#/components/schemas/Meeting"},"new_meeting":{"$ref":"#/components/schemas/Meeting"},"changed_fields":{"title":"Changed Fields","type":"array","items":{"type":"string"}}}},"MeetingEventType":{"title":"MeetingEventType","enum":["MeetingDeleted","MeetingCreated","MeetingUpdated"],"description":"An enumeration."},"NawsCode":{"title":"NawsCode","required":["bmlt_id","code","root_server_id"],"type":"object","properties":{"bmlt_id":{"title":"Bmlt Id","type":"integer"},"code":{"title":"Code","type":"string"},"root_server_id":{"title":"Root Server Id","type":"integer"}}},"NawsCodeCreate":{"title":"NawsCodeCreate","required":["bmlt_id","code"],"type":"object","properties":{"bmlt_id":{"title":"Bmlt Id","type":"integer"},"code":{"title":"Code","type":"string"}}},"RootServer":{"title":"RootServer","required":["name","url","is_enabled","id"],"type":"object","properties":{"name":{"title":"Name","maxLength":255,"minLength":1,"type":"string"},"url":{"title":"Url","maxLength":65536,"minLength":1,"type":"string","format":"uri"},"is_enabled":{"title":"Is Enabled","type":"boolean"},"id":{"title":"Id","type":"integer"}}},"RootServerCreate":{"title":"RootServerCreate","required":["name","url","is_enabled"],"type":"object","properties":{"name":{"title":"Name","maxLength":255,"minLength":1,"type":"string"},"url":{"title":"Url","maxLength":65536,"minLength":1,"type":"string","format":"uri"},"is_enabled":{"title":"Is Enabled","type":"boolean"}}},"RootServerUpdate":{"title":"RootServerUpdate","type":"object","properties":{"name":{"title":"Name","maxLength":255,"minLength":1,"type":"string"},"url":{"title":"Url","maxLength":65536,"minLength":1,"type":"string","format":"uri"},"is_enabled":{"title":"Is Enabled","type":"boolean"}}},"ServiceBody":{"title":"ServiceBody","required":["bmlt_id","parent_bmlt_id","name","type","description","url","helpline","world_id","naws_code_override"],"type":"object","properties":{"bmlt_id":{"title":"Bmlt Id","type":"integer"},"parent_bmlt_id":{"title":"Parent Bmlt Id","type":"integer"},"name":{"title":"Name","type":"string"},"type":{"title":"Type","type":"string"},"description":{"title":"Description","type":"string"},"url":{"title":"Url","type":"string"},"helpline":{"title":"Helpline","type":"string"},"world_id":{"title":"World Id","type":"string"},"naws_code_override":{"title":"Naws Code Override","type":"string"}}},"Snapshot":{"title":"Snapshot","required":["root_server_id","date"],"type":"object","properties":{"root_server_id":{"title":"Root Server Id","type":"integer"},"date":{"title":"Date","type":"string","format":"date"}}},"Token":{"title":"Token","required":["access_token","refresh_token","token_type"],"type":"object","properties":{"access_token":{"title":"Access Token","type":"string"},"refresh_token":{"title":"Refresh Token","type":"string"},"token_type":{"title":"Token Type","type":"string"}}},"User":{"title":"User","required":["username","email","is_active","is_admin","id"],"type":"object","properties":{"username":{"title":"Username","type":"string"},"email":{"title":"Email","type":"string","format":"email"},"is_active":{"title":"Is Active","type":"boolean"},"is_admin":{"title":"Is Admin","type":"boolean"},"id":{"title":"Id","type":"integer"}}},"UserCreate":{"title":"UserCreate","required":["username","email","is_active","password"],"type":"object","properties":{"username":{"title":"Username","type":"string"},"email":{"title":"Email","type":"string","format":"email"},"is_active":{"title":"Is Active","type":"boolean"},"is_admin":{"title":"Is Admin","type":"boolean","default":false},"password":{"title":"Password","type":"string"}}},"ValidationError":{"title":"ValidationError","required":["loc","msg","type"],"type":"object","properties":{"loc":{"title":"Location","type":"array","items":{"type":"string"}},"msg":{"title":"Message","type":"string"},"type":{"title":"Error Type","type":"string"}}},"VenueTypeEnum":{"title":"VenueTypeEnum","enum":[0,1,2,3],"type":"integer","description":"An enumeration."}},"securitySchemes":{"OAuth2PasswordBearer":{"type":"oauth2","flows":{"password":{"scopes":{},"tokenUrl":"token"}}}}}}